{
  "animateLoading": true,
  "borderRadius": "{{appsmith.theme.borderRadius.appBorderRadius}}",
  "bottomRow": 7,
  "dynamicBindingPathList": [
    {
      "key": "truncateButtonColor"
    },
    {
      "key": "fontFamily"
    },
    {
      "key": "borderRadius"
    },
    {
      "key": "text"
    }
  ],
  "dynamicHeight": "AUTO_HEIGHT",
  "dynamicTriggerPathList": [],
  "fontFamily": "{{appsmith.theme.fontFamily.appFont}}",
  "fontSize": "1.875rem",
  "fontStyle": "BOLD",
  "isLoading": false,
  "isVisible": true,
  "key": "crqpcoblx7",
  "leftColumn": 20,
  "maxDynamicHeight": 9000,
  "minDynamicHeight": 4,
  "minWidth": 450,
  "mobileBottomRow": 7,
  "mobileLeftColumn": 24,
  "mobileRightColumn": 40,
  "mobileTopRow": 3,
  "needsErrorInfo": false,
  "originalBottomRow": 57,
  "originalTopRow": 2,
  "overflow": "NONE",
  "parentColumnSpace": 23.382568359375,
  "parentId": "wq5trrp1or",
  "parentRowSpace": 10,
  "renderMode": "CANVAS",
  "responsiveBehavior": "fill",
  "rightColumn": 43,
  "shouldTruncate": false,
  "text": "Welcome,  {{ query_get_contact.data[0]?.first_name }}!",
  "textAlign": "CENTER",
  "textColor": "#231F20",
  "topRow": 2,
  "truncateButtonColor": "{{appsmith.theme.colors.primaryColor}}",
  "type": "TEXT_WIDGET",
  "version": 1,
  "widgetId": "h0eyvkw320",
  "widgetName": "Text1"
}