{
  "gitSyncId": "67e39fa4353a9a52f83d02a7_2a7d9c41-94a4-48bb-94ea-7beb0b274cd8",
  "id": "creare tabele_select_rating_view",
  "pluginId": "postgres-plugin",
  "pluginType": "DB",
  "unpublishedAction": {
    "actionConfiguration": {
      "body": "SELECT * FROM medic_rating_view;\n\n",
      "encodeParamsToggle": true,
      "paginationType": "NONE",
      "pluginSpecifiedTemplates": [
        {
          "value": true
        }
      ],
      "timeoutInMillisecond": 10000
    },
    "confirmBeforeExecute": false,
    "datasource": {
      "id": "clinica_medicala",
      "isAutoGenerated": false,
      "name": "clinica_medicala",
      "pluginId": "postgres-plugin"
    },
    "dynamicBindingPathList": [],
    "executeOnLoad": false,
    "name": "select_rating_view",
    "pageId": "creare tabele",
    "userSetOnLoad": false
  }
}